curldl/__init__.py
curldl/__main__.py
curldl/_version.py
curldl/cli.py
curldl/curldl.py
curldl/py.typed
curldl/util/__init__.py
curldl/util/crypt.py
curldl/util/fs.py
curldl/util/log.py
curldl/util/time.py
curldl-1.0.1.dist-info/LICENSE.md
curldl-1.0.1.dist-info/METADATA
curldl-1.0.1.dist-info/WHEEL
curldl-1.0.1.dist-info/entry_points.txt
curldl-1.0.1.dist-info/top_level.txt
curldl-1.0.1.dist-info/RECORD
