Metadata-Version: 2.1
Name: curldl
Version: 1.0.1
Summary: Safely and reliably download files with PycURL
Author-email: Michael Orlov <orlovm@noexec.org>
License: LGPL-3.0-or-later
Project-URL: Homepage, https://github.com/noexec/curldl
Project-URL: Documentation, https://curldl.readthedocs.io/
Project-URL: Bug Tracker, https://github.com/noexec/curldl/issues
Project-URL: Changelog, https://github.com/noexec/curldl/blob/develop/docs/CHANGELOG.md
Keywords: cURL,PycURL,download
Classifier: Development Status :: 5 - Production/Stable
Classifier: Environment :: Console
Classifier: Intended Audience :: Developers
Classifier: Intended Audience :: System Administrators
Classifier: License :: OSI Approved :: GNU Lesser General Public License v3 or later (LGPLv3+)
Classifier: Operating System :: OS Independent
Classifier: Programming Language :: Python
Classifier: Programming Language :: Python :: 3 :: Only
Classifier: Programming Language :: Python :: 3.8
Classifier: Programming Language :: Python :: 3.11
Classifier: Topic :: Software Development :: Libraries :: Python Modules
Classifier: Topic :: Internet :: WWW/HTTP
Classifier: Topic :: Internet :: File Transfer Protocol (FTP)
Classifier: Topic :: System :: Networking
Requires-Python: >=3.8
License-File: LICENSE.md
Requires-Dist: pycurl >=7.44.0
Requires-Dist: tenacity >=6.2.0
Requires-Dist: tqdm >=4.50.0
Provides-Extra: dev
Requires-Dist: build ; extra == 'dev'
Requires-Dist: ipython ; extra == 'dev'
Requires-Dist: pipdeptree ; extra == 'dev'
Requires-Dist: pip-autoremove ; extra == 'dev'
Requires-Dist: pip-review ; extra == 'dev'
Requires-Dist: towncrier ; extra == 'dev'
Requires-Dist: twine ; extra == 'dev'
Requires-Dist: wheel ; extra == 'dev'
Provides-Extra: doc
Requires-Dist: myst-parser[linkify] ; extra == 'doc'
Requires-Dist: sphinx >=7 ; extra == 'doc'
Requires-Dist: sphinx-copybutton ; extra == 'doc'
Requires-Dist: furo ; extra == 'doc'
Provides-Extra: minimal
Requires-Dist: pycurl ==7.44.0 ; extra == 'minimal'
Requires-Dist: tenacity ==6.2.0 ; extra == 'minimal'
Requires-Dist: tqdm ==4.50.0 ; extra == 'minimal'
Provides-Extra: test
Requires-Dist: bandit[toml] ; extra == 'test'
Requires-Dist: pytest ; extra == 'test'
Requires-Dist: pytest-black-ng ; extra == 'test'
Requires-Dist: pytest-cov ; extra == 'test'
Requires-Dist: pytest-httpserver ; extra == 'test'
Requires-Dist: pytest-isort ; extra == 'test'
Requires-Dist: pytest-mock ; extra == 'test'
Requires-Dist: pytest-mypy ; extra == 'test'
Requires-Dist: pytest-pylint ; extra == 'test'
Requires-Dist: pytest-repeat ; extra == 'test'
Requires-Dist: pytest-sugar ; extra == 'test'
Requires-Dist: pytest-xdist[psutil] ; extra == 'test'
Requires-Dist: setuptools-scm[toml] ; extra == 'test'
Requires-Dist: types-pycurl ; extra == 'test'
Requires-Dist: types-tqdm ; extra == 'test'
